ya_activity/__init__.py
ya_activity/api_client.py
ya_activity/configuration.py
ya_activity/exceptions.py
ya_activity/rest.py
ya_activity/api/__init__.py
ya_activity/api/provider_api.py
ya_activity/api/requestor_control_api.py
ya_activity/api/requestor_state_api.py
ya_activity/models/__init__.py
ya_activity/models/activity_state.py
ya_activity/models/activity_usage.py
ya_activity/models/create_activity.py
ya_activity/models/create_activity_all_of.py
ya_activity/models/destroy_activity.py
ya_activity/models/error_message.py
ya_activity/models/exe_script_command_result.py
ya_activity/models/exe_script_command_state.py
ya_activity/models/exe_script_request.py
ya_activity/models/get_activity_state.py
ya_activity/models/get_activity_usage.py
ya_activity/models/provider_event.py
ya_client_activity-0.1.0.dist-info/METADATA
ya_client_activity-0.1.0.dist-info/WHEEL
ya_client_activity-0.1.0.dist-info/top_level.txt
ya_client_activity-0.1.0.dist-info/RECORD
