Metadata-Version: 2.1
Name: ya-client-activity
Version: 0.1.0
Summary: Yagna Activity API
Home-page: UNKNOWN
Author: OpenAPI Generator community
Author-email: team@openapitools.org
License: UNKNOWN
Keywords: OpenAPI,OpenAPI-Generator,Yagna Activity API
Platform: UNKNOWN
Requires-Dist: urllib3 (>=1.15)
Requires-Dist: six (>=1.10)
Requires-Dist: certifi
Requires-Dist: python-dateutil
Requires-Dist: aiohttp (>=3.0.0)
